Metadata-Version: 1.0
Name: mcplaystats
Version: 1.0.0
Summary: Unofficial API Wrapper for McPlayHD API
Home-page: UNKNOWN
Author: Mythological
Author-email: UNKNOWN
License: MIT
Platform: UNKNOWN
